sharepoint/__init__.py
sharepoint/_api.py
sharepoint/_base.py
sharepoint/_datetime_utils.py
sharepoint/_odata_utils.py
sharepoint/exceptions.py
sharepoint/folder.py
sharepoint/group.py
sharepoint/list.py
sharepoint/list_field.py
sharepoint/list_item.py
sharepoint/list_item_version.py
sharepoint/site.py
sharepoint/user.py
sharepoint_v1_api-1.0.2.dist-info/licenses/LICENSE
sharepoint_v1_api-1.0.2.dist-info/METADATA
sharepoint_v1_api-1.0.2.dist-info/WHEEL
sharepoint_v1_api-1.0.2.dist-info/top_level.txt
sharepoint_v1_api-1.0.2.dist-info/RECORD
