Metadata-Version: 2.4
Name: sharepoint_v1_api
Version: 1.0.2
Author: Aske Bluhme Klok
License: MIT
Keywords: Sharepoint
Classifier: Programming Language :: Python :: 3
Classifier: Development Status :: 4 - Beta
Classifier: Intended Audience :: Developers
Classifier: License :: OSI Approved :: MIT License
Classifier: Operating System :: OS Independent
Requires-Python: >=3.9
License-File: LICENSE
Requires-Dist: requests>=2.32.2
Requires-Dist: requests-ntlm>=1.3.0
Dynamic: author
Dynamic: classifier
Dynamic: description
Dynamic: description-content-type
Dynamic: keywords
Dynamic: license
Dynamic: license-file
Dynamic: requires-dist
Dynamic: requires-python
